cryptg/__init__.py
cryptg/cryptg.cpython-311-aarch64-linux-gnu.so
cryptg/cryptg.pyi
cryptg/py.typed
cryptg-0.5.2.dist-info/METADATA
cryptg-0.5.2.dist-info/WHEEL
cryptg-0.5.2.dist-info/top_level.txt
cryptg-0.5.2.dist-info/RECORD
cryptg-0.5.2.dist-info/licenses/LICENSE.txt
