Metadata-Version: 2.4
Name: cryptg
Version: 0.5.2
Summary: Cryptographic utilities for Telegram.
Home-page: https://github.com/cher-nov/cryptg
Download-URL: https://github.com/cher-nov/cryptg/releases
Author: Dmitry D. Chernov; Lonami E
Author-email: blackdoomer@yandex.ru
License: CC0
Keywords: telegram crypto cryptography mtproto aes
Classifier: Development Status :: 4 - Beta
Classifier: Intended Audience :: Developers
Classifier: Topic :: Security :: Cryptography
Classifier: License :: CC0 1.0 Universal (CC0 1.0) Public Domain Dedication
Classifier: Programming Language :: Python :: 3
Classifier: Programming Language :: Python :: 3.7
Classifier: Programming Language :: Python :: 3.8
Classifier: Programming Language :: Python :: 3.9
Classifier: Programming Language :: Python :: 3.10
Classifier: Programming Language :: Python :: 3.11
Requires-Python: >=3.7
License-File: LICENSE.txt
Dynamic: author
Dynamic: author-email
Dynamic: classifier
Dynamic: description
Dynamic: description-content-type
Dynamic: download-url
Dynamic: home-page
Dynamic: keywords
Dynamic: license
Dynamic: license-file
Dynamic: requires-python
Dynamic: summary
